CHANGES.md
LICENSE.txt
MANIFEST.in
README.rst
setup.py
pyin/__init__.py
pyin/cli.py
pyin/core.py
pyin.egg-info/PKG-INFO
pyin.egg-info/SOURCES.txt
pyin.egg-info/dependency_links.txt
pyin.egg-info/entry_points.txt
pyin.egg-info/requires.txt
pyin.egg-info/top_level.txt
pyin.egg-info/zip-safe
tests/__init__.py
tests/module.py
tests/test_cli.py
tests/test_core.py