Metadata-Version: 1.1
Name: pyin
Version: 0.5.2
Summary: basic streaming text processing
Home-page: https://github.com/geowurster/pyin
Author: Kevin Wurster
Author-email: wursterk@gmail.com
License: MIT
Platform: UNKNOWN
Classifier: Development Status :: 4 - Beta
Classifier: Intended Audience :: Developers
Classifier: License :: OSI Approved :: BSD License
Classifier: Topic :: Text Processing :: Filters
Classifier: Topic :: Text Processing :: General
Classifier: Topic :: Utilities
